etiya_ie/__init__.py
etiya_ie/count_row.py
etiya_ie/csv_to_sql.py
etiya_ie/join_funcs.py
etiya_ie/ssh_funcs.py
etiya_ie-0.1.0.dist-info/METADATA
etiya_ie-0.1.0.dist-info/WHEEL
etiya_ie-0.1.0.dist-info/top_level.txt
etiya_ie-0.1.0.dist-info/RECORD
